trako
