Metadata-Version: 2.1
Name: trako
Version: 0.3.4.dev9
Summary: The TRAKO Project: Compression of DTI Streamlines.
Home-page: https://github.com/haehn/TRAKO
Author: Daniel Haehn
Author-email: haehn@mpsych.org
License: UNKNOWN
Platform: UNKNOWN
Classifier: Programming Language :: Python :: 3
Classifier: License :: OSI Approved :: MIT License
Classifier: Operating System :: OS Independent
Requires-Python: >=3.6
